pywordlist/__init__.py
pywordlist/wordlist.py
pywordlist-0.0.2.dist-info/DESCRIPTION.rst
pywordlist-0.0.2.dist-info/METADATA
pywordlist-0.0.2.dist-info/RECORD
pywordlist-0.0.2.dist-info/WHEEL
pywordlist-0.0.2.dist-info/metadata.json
pywordlist-0.0.2.dist-info/top_level.txt
pywordlist-0.0.2.dist-info/zip-safe
